ISMgas/GalaxyProperties.py
ISMgas/SupportingFunctions.py
ISMgas/__init__.py
ISMgas/globalVars.py
ISMgas/linelist.py
ISMgas/fitting/DoubleGaussian.py
ISMgas/fitting/init_fitting.py
ISMgas/humvi/humvi.py
ISMgas/kcwi/kcwiFunctions.py
ISMgas/kcwi/kcwiReduction.py
ISMgas/spectra/AnalyzeSpectra.py
ISMgas-0.0.3.dist-info/LICENSE
ISMgas-0.0.3.dist-info/METADATA
ISMgas-0.0.3.dist-info/WHEEL
ISMgas-0.0.3.dist-info/top_level.txt
ISMgas-0.0.3.dist-info/RECORD
