Metadata-Version: 2.1
Name: ISMgas
Version: 0.0.3
Summary: ISMgas is a python module used to analyze absorption line kinematics of Interstellar Medium gas.
Author-email: "Keerthi Vasan G.C." <kvch@ucdavis.edu>
Project-URL: Homepage, https://github.com/kvgc/ISMgas
Project-URL: Issues, https://github.com/kvgc/ISMgas/issues
Classifier: Programming Language :: Python :: 3
Classifier: License :: OSI Approved :: MIT License
Classifier: Operating System :: OS Independent
Requires-Python: >=3.8
License-File: LICENSE
